LICENSE
README.md
setup.cfg
setup.py
Topsis_Cherish_102003647/topsis.py
Topsis_Cherish_102003647.egg-info/PKG-INFO
Topsis_Cherish_102003647.egg-info/SOURCES.txt
Topsis_Cherish_102003647.egg-info/dependency_links.txt
Topsis_Cherish_102003647.egg-info/requires.txt
Topsis_Cherish_102003647.egg-info/top_level.txt