Metadata-Version: 2.1
Name: Topsis-Cherish-102003647
Version: 0.4
Summary: It is a topsis package.
Home-page: https://github.com/15cherish/Topsis-Cherish-102003647
Author: Cherish Mahajan
Author-email: cherishmahajan@gmail.com
License: MIT
Download-URL: https://github.com/15cherish/Topsis-Cherish-102003647/archive/refs/tags/0.2.tar.gz
Keywords: MCDM,102003647,TOPSIS
Platform: UNKNOWN
Classifier: Development Status :: 3 - Alpha
Classifier: Intended Audience :: Developers
Classifier: Topic :: Software Development :: Build Tools
Classifier: License :: OSI Approved :: MIT License
Classifier: Programming Language :: Python :: 3
Classifier: Programming Language :: Python :: 3.4
Classifier: Programming Language :: Python :: 3.5
Classifier: Programming Language :: Python :: 3.6
Classifier: Programming Language :: Python :: 3.7
Classifier: Programming Language :: Python :: 3.8
